{
  "id": "example-direct-push",
  "kind": "direct-push",
  "sha": "def4567890def4567890def4567890def4567890",
  "author": "octocat",
  "authorUrl": "https://github.com/octocat",
  "committedAt": "2026-05-01T08:30:00Z",
  "commitUrl": "https://github.com/octocat/example/commit/def4567890def4567890def4567890def4567890",
  "headline": "A typo in the readme, fixed at the speed of caffeine",
  "standfirst": "One letter, no review, committed straight to main with the kind of confidence reserved for documentation.",
  "body": "The change is a single character. The commit message is the change. There is nothing more to say, but the development log notes it anyway, because that is what development logs are for."
}
